isyndicate/__init__.py
isyndicate/exceptions.py
isyndicate-1.0.0.dist-info/LICENSE
isyndicate-1.0.0.dist-info/METADATA
isyndicate-1.0.0.dist-info/WHEEL
isyndicate-1.0.0.dist-info/top_level.txt
isyndicate-1.0.0.dist-info/RECORD
